CONTRIBUTING.rst
HISTORY.rst
LICENSE
MANIFEST.in
README.md
setup.cfg
setup.py
brainstorm/__about__.py
brainstorm/__init__.py
brainstorm/all.py
brainstorm/data_iterators.py
brainstorm/describable.py
brainstorm/hooks.py
brainstorm/initializers.py
brainstorm/optional.py
brainstorm/randomness.py
brainstorm/scorers.py
brainstorm/tools.py
brainstorm/utils.py
brainstorm/value_modifiers.py
brainstorm.egg-info/PKG-INFO
brainstorm.egg-info/SOURCES.txt
brainstorm.egg-info/dependency_links.txt
brainstorm.egg-info/requires.txt
brainstorm.egg-info/top_level.txt
brainstorm/handlers/__init__.py
brainstorm/handlers/_cpuop.c
brainstorm/handlers/_cpuop.pyx
brainstorm/handlers/base_handler.py
brainstorm/handlers/debug_handler.py
brainstorm/handlers/numpy_handler.py
brainstorm/handlers/pycuda_handler.py
brainstorm/layers/__init__.py
brainstorm/layers/base_layer.py
brainstorm/layers/batch_normalization_layer.py
brainstorm/layers/binomial_cross_entropy_layer.py
brainstorm/layers/clockwork_layer.py
brainstorm/layers/clockwork_lstm_layer.py
brainstorm/layers/convolution_layer_2d.py
brainstorm/layers/deltas_scaling_layer.py
brainstorm/layers/dropout_layer.py
brainstorm/layers/elementwise_layer.py
brainstorm/layers/fully_connected_layer.py
brainstorm/layers/highway_layer.py
brainstorm/layers/input_layer.py
brainstorm/layers/l1_decay.py
brainstorm/layers/l2_decay.py
brainstorm/layers/loss_layer.py
brainstorm/layers/lstm_layer.py
brainstorm/layers/mask_layer.py
brainstorm/layers/merge_layer.py
brainstorm/layers/noop_layer.py
brainstorm/layers/pooling_layer_2d.py
brainstorm/layers/recurrent_layer.py
brainstorm/layers/sigmoid_ce_layer.py
brainstorm/layers/softmax_ce_layer.py
brainstorm/layers/squared_difference_layer.py
brainstorm/layers/squared_error_layer.py
brainstorm/structure/__init__.py
brainstorm/structure/architecture.py
brainstorm/structure/buffer_structure.py
brainstorm/structure/buffer_views.py
brainstorm/structure/buffers.py
brainstorm/structure/construction.py
brainstorm/structure/layout.py
brainstorm/structure/network.py
brainstorm/structure/view_references.py
brainstorm/training/__init__.py
brainstorm/training/schedules.py
