Metadata-Version: 1.1
Name: brainstorm
Version: 0.5
Summary: Fast, flexible and fun neural networks.
Home-page: https://github.com/IDSIA/brainstorm
Author: The Swiss AI Lab IDSIA
Author-email: mailstorm@googlemail.com
License: MIT
Platform: UNKNOWN
Classifier: Development Status :: 4 - Beta
Classifier: Intended Audience :: Developers
Classifier: Intended Audience :: Science/Research
Classifier: Intended Audience :: Education
Classifier: License :: OSI Approved :: MIT License
Classifier: Natural Language :: English
Classifier: Programming Language :: Python :: 2.7
Classifier: Programming Language :: Python :: 3.3
